{
  "type": "forge:conditional",
  "recipes": [
    {
      "conditions": [
        {
          "type": "simplemusket:netherite_enabled"
        }
      ],
      "recipe": {
        "type": "minecraft:crafting_shaped",
        "key": {
          "C": {
            "item": "minecraft:netherite_ingot"
          },
          "G": {
            "item": "minecraft:gunpowder"
          },
          "P": {
            "item": "minecraft:paper"
          }
        },
        "pattern": [
          " C ",
          " G ",
          " P "
        ],
        "result": {
          "count": 8,
          "item": "simplemusket:netherite_bullet"
        }
      }
    }
  ]
}